spedpytools/__init__.py
spedpytools/efd_handler.py
spedpytools-0.1.1.dist-info/LICENSE
spedpytools-0.1.1.dist-info/METADATA
spedpytools-0.1.1.dist-info/WHEEL
spedpytools-0.1.1.dist-info/top_level.txt
spedpytools-0.1.1.dist-info/RECORD
