Metadata-Version: 2.1
Name: spedpytools
Version: 0.1.1
Summary: Biblioteca para visualização de um arquivo sped em estrutura de tabelas do Pandas e possibilidade de salvar em formato para excel.
Author: Ismael Nascimento
Author-email: ismaelnjr@icloud.com.br
License: MIT License
Keywords: sped fiscal receita federal
Classifier: Programming Language :: Python :: 3
Classifier: License :: OSI Approved :: MIT License
Classifier: Operating System :: OS Independent
Requires-Python: >=3.6
License-File: LICENSE
Requires-Dist: openpyxl==3.1.5
Requires-Dist: pandas==2.2.3
Requires-Dist: spedpy>=1.1.6
Requires-Dist: tdqm==0.0.1
